django_steamauth-1.1.1.dist-info/METADATA
django_steamauth-1.1.1.dist-info/RECORD
django_steamauth-1.1.1.dist-info/WHEEL
django_steamauth-1.1.1.dist-info/top_level.txt
steamauth/__init__.py
steamauth/steamauth.py
