Metadata-Version: 2.1
Name: django-steamauth
Version: 1.1.1
Summary: steam login library for django
Home-page: https://github.com/blurfx/django-steamauth
Author: blurfx
Author-email: pipsit@gmail.com
License: MIT License
Keywords: django,steam,valve,steamid,openid
Platform: UNKNOWN
Classifier: Development Status :: 5 - Production/Stable
Classifier: Intended Audience :: Developers
Classifier: Programming Language :: Python
Classifier: Programming Language :: Python :: 3
Classifier: Programming Language :: Python :: 2
Classifier: Operating System :: OS Independent
Classifier: Intended Audience :: Developers
Classifier: Framework :: Django
Classifier: Framework :: Django :: 1.10
Classifier: Framework :: Django :: 2.0
Classifier: License :: OSI Approved :: MIT License
